dinosaur/__init__.py
dinosaur/associated_legendre.py
dinosaur/associated_legendre_test.py
dinosaur/coordinate_systems.py
dinosaur/coordinate_systems_test.py
dinosaur/filtering.py
dinosaur/filtering_test.py
dinosaur/fourier.py
dinosaur/fourier_test.py
dinosaur/held_suarez.py
dinosaur/held_suarez_test.py
dinosaur/horizontal_interpolation.py
dinosaur/horizontal_interpolation_test.py
dinosaur/hybrid_coordinates.py
dinosaur/hybrid_coordinates_test.py
dinosaur/jax_numpy_utils.py
dinosaur/jax_numpy_utils_test.py
dinosaur/layer_coordinates.py
dinosaur/primitive_equations.py
dinosaur/primitive_equations_integration_test.py
dinosaur/primitive_equations_states.py
dinosaur/primitive_equations_test.py
dinosaur/pytree_utils.py
dinosaur/pytree_utils_test.py
dinosaur/radiation.py
dinosaur/radiation_test.py
dinosaur/scales.py
dinosaur/scales_test.py
dinosaur/shallow_water.py
dinosaur/shallow_water_states.py
dinosaur/shallow_water_states_test.py
dinosaur/shallow_water_test.py
dinosaur/sigma_coordinates.py
dinosaur/sigma_coordinates_test.py
dinosaur/spherical_harmonic.py
dinosaur/spherical_harmonic_test.py
dinosaur/time_integration.py
dinosaur/time_integration_test.py
dinosaur/typing.py
dinosaur/vertical_interpolation.py
dinosaur/vertical_interpolation_test.py
dinosaur/weatherbench_utils.py
dinosaur/xarray_utils.py
dinosaur/xarray_utils_test.py
dinosaur/data/ecmwf137_hybrid_levels.csv
dinosaur/data/ufs127_hybrid_levels.csv
dinosaur-1.3.5.dist-info/licenses/LICENSE
dinosaur-1.3.5.dist-info/METADATA
dinosaur-1.3.5.dist-info/WHEEL
dinosaur-1.3.5.dist-info/top_level.txt
dinosaur-1.3.5.dist-info/RECORD
