Metadata-Version: 2.4
Name: dinosaur
Version: 1.3.5
Summary: Differentiable Dynamics for Global Atmospheric Modeling 🦖
Author-email: Google LLC <noreply@google.com>
License-Expression: Apache-2.0
Project-URL: source, https://github.com/neuralgcm/dinosaur
Requires-Python: >=3.10
License-File: LICENSE
Requires-Dist: jax
Requires-Dist: jaxlib
Requires-Dist: numpy
Requires-Dist: pint
Requires-Dist: scipy
Requires-Dist: scikit-learn
Requires-Dist: tree-math
Requires-Dist: dask
Requires-Dist: fsspec
Requires-Dist: pandas
Requires-Dist: xarray
Requires-Dist: xarray-tensorstore
Provides-Extra: tests
Requires-Dist: absl-py; extra == "tests"
Requires-Dist: chex; extra == "tests"
Requires-Dist: pytest; extra == "tests"
Dynamic: license-file
